mypackage/__init__.py
mypackage/customSort.py
CDCNProject-0.0.3.dist-info/LICENSE
CDCNProject-0.0.3.dist-info/METADATA
CDCNProject-0.0.3.dist-info/WHEEL
CDCNProject-0.0.3.dist-info/top_level.txt
CDCNProject-0.0.3.dist-info/RECORD
