Metadata-Version: 2.1
Name: CDCNProject
Version: 0.0.3
Summary: A example package
Home-page: https://github.com/cyantiz/shoe-shop
Author: Kaito
Author-email: kaitok57a01@gmail.com
Project-URL: Bug Tracker, https://github.com/cyantiz/shoe-shop/issues
Classifier: Programming Language :: Python :: 3
Classifier: License :: OSI Approved :: MIT License
Classifier: Operating System :: OS Independent
Requires-Python: >=3.6
License-File: LICENSE
